README.md
setup.py
torch_metrics/__init__.py
torch_metrics/utils.py
torch_metrics.egg-info/PKG-INFO
torch_metrics.egg-info/SOURCES.txt
torch_metrics.egg-info/dependency_links.txt
torch_metrics.egg-info/top_level.txt