Metadata-Version: 1.0
Name: torch-metrics
Version: 1.1.7
Summary: Metrics for model evaluation in pytorch
Home-page: https://github.com/chinokenochkan/torch-metrics
Author: Chi Nok Enoch Kan @chinokenochkan
Author-email: kanxx030@gmail.com
License: UNKNOWN
Platform: UNKNOWN
